docxtpl/__init__.py
docxtpl/__main__.py
docxtpl/inline_image.py
docxtpl/listing.py
docxtpl/richtext.py
docxtpl/subdoc.py
docxtpl/template.py
docxtpl2-0.18.1.dist-info/LICENSE.txt
docxtpl2-0.18.1.dist-info/METADATA
docxtpl2-0.18.1.dist-info/WHEEL
docxtpl2-0.18.1.dist-info/eager_resources.txt
docxtpl2-0.18.1.dist-info/top_level.txt
docxtpl2-0.18.1.dist-info/RECORD
