Metadata-Version: 2.1
Name: docxtpl2
Version: 0.18.1
Summary: Python docx template engine (with bayoo-docx dependency)
Home-page: https://github.com/PasaOpasen/python-docx-template2
Author: Eric Lapouyade
License: LGPL 2.1
Keywords: jinja2
Platform: UNKNOWN
Classifier: Intended Audience :: Developers
Classifier: Development Status :: 4 - Beta
Classifier: Programming Language :: Python :: 3
Classifier: Programming Language :: Python :: 3.7
Classifier: Programming Language :: Python :: 3.8
Classifier: Programming Language :: Python :: 3.9
Classifier: Programming Language :: Python :: 3.10
Classifier: Programming Language :: Python :: 3.11
Classifier: Programming Language :: Python :: 3.12
Requires-Dist: bayoo-docx
Requires-Dist: docxcompose2
Requires-Dist: jinja2
Requires-Dist: lxml
Provides-Extra: docs
Requires-Dist: Sphinx; extra == "docs"
Requires-Dist: sphinxcontrib-napoleon; extra == "docs"
